graph_generator_assistant/__init__.py
graph_generator_assistant/about.py
graph_generator_assistant/color_picker.py
graph_generator_assistant/desktop.py
graph_generator_assistant/program.py
graph_generator_assistant/icons/color_picker.png
graph_generator_assistant/icons/logo.png
graph_generator_assistant/images/laptop.png
graph_generator_assistant/images/pc.png
graph_generator_assistant/images/phone.png
graph_generator_assistant/images/router.png
graph_generator_assistant/images/switch.png
graph_generator_assistant/images/tablet.png
graph_generator_assistant/modules/__init__.py
graph_generator_assistant/modules/lib_about.py
graph_generator_assistant/modules/lib_data.py
graph_generator_assistant/modules/lib_execute.py
graph_generator_assistant/modules/lib_files.py
graph_generator_assistant/modules/lib_funcs.py
graph_generator_assistant/templates/__init__.py
graph_generator_assistant/templates/bubble_chart1.json
graph_generator_assistant/templates/bubble_chart1.png
graph_generator_assistant/templates/bubble_chart1.py
graph_generator_assistant/templates/bubble_chart2.json
graph_generator_assistant/templates/bubble_chart2.png
graph_generator_assistant/templates/bubble_chart2.py
graph_generator_assistant/templates/chart_relation_class.json
graph_generator_assistant/templates/chart_relation_class.png
graph_generator_assistant/templates/chart_relation_class.py
graph_generator_assistant/templates/chart_relation_r2.json
graph_generator_assistant/templates/chart_relation_r2.png
graph_generator_assistant/templates/chart_relation_r2.py
graph_generator_assistant/templates/circular_diagram1.json
graph_generator_assistant/templates/circular_diagram1.png
graph_generator_assistant/templates/circular_diagram1.py
graph_generator_assistant/templates/clustered_bar_chart1.json
graph_generator_assistant/templates/clustered_bar_chart1.png
graph_generator_assistant/templates/clustered_bar_chart1.py
graph_generator_assistant/templates/confusion_matrix1.json
graph_generator_assistant-0.1.4.dist-info/licenses/LICENSE
graph_generator_assistant-0.1.4.dist-info/METADATA
graph_generator_assistant-0.1.4.dist-info/WHEEL
graph_generator_assistant-0.1.4.dist-info/entry_points.txt
graph_generator_assistant-0.1.4.dist-info/top_level.txt
graph_generator_assistant-0.1.4.dist-info/RECORD
