Metadata-Version: 2.4
Name: graph_generator_assistant
Version: 0.1.4
Summary: Program that assists in generating professional graphs.
Author-email: Fernando Pujaico Rivera <fernando.pujaico.rivera@gmail.com>
Maintainer-email: Fernando Pujaico Rivera <fernando.pujaico.rivera@gmail.com>
License-Expression: GPL-3.0-only WITH Classpath-exception-2.0 OR BSD-3-Clause
Project-URL: Bug Reports, https://github.com/trucomanx/GraphGeneratorAssistant/issues
Project-URL: Funding, https://trucomanx.github.io/en/funding.html
Project-URL: Documentation, https://github.com/trucomanx/GraphGeneratorAssistant/tree/main/doc
Project-URL: Source, https://github.com/trucomanx/GraphGeneratorAssistant
Keywords: writing,translate
Classifier: Programming Language :: Python :: 3
Classifier: Operating System :: OS Independent
Requires-Python: >=3.8
License-File: LICENSE
Requires-Dist: PyQt5
Requires-Dist: deep-consultation
Requires-Dist: matplotlib
Requires-Dist: networkx
Requires-Dist: numpy
Requires-Dist: scikit-learn
Requires-Dist: pillow
Requires-Dist: pyautogui
Requires-Dist: pynput
Requires-Dist: scipy
Requires-Dist: squarify
Dynamic: license-file
